LICENSE
MANIFEST.in
README.rst
setup.cfg
setup.py
src/basicstruct.py
src/basicstruct.egg-info/PKG-INFO
src/basicstruct.egg-info/SOURCES.txt
src/basicstruct.egg-info/dependency_links.txt
src/basicstruct.egg-info/requires.txt
src/basicstruct.egg-info/top_level.txt