Metadata-Version: 1.1
Name: basicstruct
Version: 1.0.3
Summary: A simple struct-like object for Python
Home-page: https://github.com/Nurdok/basicstruct/
Author: Amir Rachum
Author-email: amir@rachum.com
License: MIT
Keywords: struct,bean,basic struct,record,slots
Platform: UNKNOWN
Classifier: Intended Audience :: Developers
Classifier: Programming Language :: Python :: 2
Classifier: Programming Language :: Python :: 3
Classifier: Operating System :: OS Independent
Classifier: License :: OSI Approved :: MIT License
